intek/__init__.py
intek/dslr/__init__.py
intek/dslr/client/__init__.py
intek/dslr/client/service/__init__.py
intek/dslr/client/service/route/__init__.py
intek/dslr/client/service/route/route_service.py
photo_geotag_restful_api_client_library-1.2.1.dist-info/METADATA
photo_geotag_restful_api_client_library-1.2.1.dist-info/WHEEL
photo_geotag_restful_api_client_library-1.2.1.dist-info/top_level.txt
photo_geotag_restful_api_client_library-1.2.1.dist-info/RECORD
