Metadata-Version: 2.1
Name: photo-geotag-restful-api-client-library
Version: 1.2.1
Summary: DSLR Photo Geotag RESTful API Client Python Library
Home-page: UNKNOWN
Author: Daniel CAUNE
Author-email: daniel.caune@gmail.com
License: MIT
Platform: any
Classifier: Development Status :: 5 - Production/Stable
Classifier: License :: OSI Approved :: MIT License
Classifier: Operating System :: OS Independent
Classifier: Programming Language :: Python
Classifier: Topic :: Software Development :: Libraries
Requires-Python: >=3
Requires-Dist: perseus-restful-api-client-library
Requires-Dist: wheel
Requires-Dist: twine
Requires-Dist: setuptools
Requires-Dist: pipfile
